liuyix_foo/__init__.py
liuyix_foo-0.1.dist-info/DESCRIPTION.rst
liuyix_foo-0.1.dist-info/METADATA
liuyix_foo-0.1.dist-info/RECORD
liuyix_foo-0.1.dist-info/WHEEL
liuyix_foo-0.1.dist-info/metadata.json
liuyix_foo-0.1.dist-info/top_level.txt
